ppbenviron/__init__.py
django_environ_ppb-1.0.1.dist-info/LICENSE
django_environ_ppb-1.0.1.dist-info/METADATA
django_environ_ppb-1.0.1.dist-info/WHEEL
django_environ_ppb-1.0.1.dist-info/top_level.txt
django_environ_ppb-1.0.1.dist-info/RECORD
