Metadata-Version: 2.1
Name: django-environ-ppb
Version: 1.0.1
Summary: easy 12factor for django settings
Home-page: https://github.com/surface-security/django-environ-ppb
Author: PPB - InfoSec Engineering
Author-email: surface@paddypowerbetfair.com
License: MIT
Classifier: Development Status :: 5 - Production/Stable
Classifier: Framework :: Django
Classifier: License :: OSI Approved :: MIT License
Classifier: Intended Audience :: Developers
Classifier: Operating System :: OS Independent
Classifier: Programming Language :: Python
Classifier: Programming Language :: Python :: 3.7
Classifier: Programming Language :: Python :: 3.8
Classifier: Programming Language :: Python :: 3.9
Classifier: Programming Language :: Python :: 3.10
Classifier: Programming Language :: Python :: 3.11
Classifier: Environment :: Web Environment
Classifier: Topic :: Software Development
Requires-Python: >=3.7
License-File: LICENSE
Requires-Dist: django-environ ==0.10.0
Provides-Extra: vault
Requires-Dist: hvac ==0.10.5 ; extra == 'vault'
